Workbook

Sheet Annahmen
A1: FieldApp SHK – Pricing-Modell
A2: Annahmen & Eingaben
A4: PRICING
A5: Preis pro User / Monat | B5: 19 | C5: Empfehlung: €15–25 (Marktstandard SHK-Software)
A6: Mindest-User pro Account | B6: 2 | C6: Kein 1-User-Account – schützt Mindestmarge
A7: Mindest-MRR pro Account | B7: =B5*B6 -> 38 | C7: Formel: Preis × Mindest-User
A8: Rabatt Jahresabo | B8: 0.1 | C8: Anreiz für Vorauszahlung – verbessert Cashflow
A10: LAUFENDE KOSTEN (MONATLICH)
A11: Infrastruktur fix (Supabase Pro, Domain, etc.) | B11: 60 | C11: Supabase Pro $25 + Hosting + Domain ≈ €60/Monat
A12: Zahlungsabwicklung (Stripe-Gebühr %) | B12: 0.014 | C12: 1,4 % + 0,25 € pro Transaktion (EU-Karten)
A13: Stripe Fixgebühr je Transaktion | B13: 0.25 | C13: Pro Abbuchung – relevant bei wenigen Usern
A14: Support-Aufwand je Account (Schätzung) | B14: 5 | C14: Erfahrungswert: ~20 Min/Monat à €15/h
A15: Entwicklung / Wartung (Ø monatlich) | B15: 400 | C15: Bug-Fixes, Updates, neue Features
A17: KUNDENSEGMENTE (Referenzwerte)
A18: Segment | B18: Ø User | C18: Ø MRR/Kd.
A19: Klein (1–5 Monteure) | B19: 3 | C19: =B5*B19 -> 57
A20: Mittel (5–20 Monteure) | B20: 9 | C20: =B5*B20 -> 171

Sheet Szenarien
A1: Umsatz-Szenarien
B2: Pessimistisch | C2: Realistisch | D2: Optimistisch
A3: EINGABEN
A4: Anzahl Kunden (Accounts) | B4: 10 | C4: 30 | D4: 75
A5: Ø User je Kunde | B5: 2.5 | C5: 3.5 | D5: 5
A6: Anteil Jahresabo (%) | B6: 0.1 | C6: 0.25 | D6: 0.4
A7: MONATLICHE KENNZAHLEN
A8: Gesamt-User | B8: =B4*B5 -> 25 | C8: =C4*C5 -> 105 | D8: =D4*D5 -> 375
A9: MRR (Monatsumsatz) | B9: =Annahmen!B5*B8 -> 475 | C9: =Annahmen!B5*C8 -> 1995 | D9: =Annahmen!B5*D8 -> 7125
A10: ARR (Jahresumsatz) | B10: =B9*12 -> 5700 | C10: =C9*12 -> 23940 | D10: =D9*12 -> 85500
A11: Infra-Kosten fix | B11: =Annahmen!B11 -> 60 | C11: =Annahmen!B11 -> 60 | D11: =Annahmen!B11 -> 60
A12: Stripe-Kosten | B12: =(B9*Annahmen!B12)+(B4*Annahmen!B13) -> 9.15 | C12: =(C9*Annahmen!B12)+(C4*Annahmen!B13) -> 35.43 | D12: =(D9*Annahmen!B12)+(D4*Annahmen!B13) -> 118.5
A13: Support-Kosten | B13: =B4*Annahmen!B14 -> 50 | C13: =C4*Annahmen!B14 -> 150 | D13: =D4*Annahmen!B14 -> 375
A14: Entwicklungskosten | B14: =Annahmen!B15 -> 400 | C14: =Annahmen!B15 -> 400 | D14: =Annahmen!B15 -> 400
A15: Gesamtkosten | B15: =SUM(B11:B14) -> 519.15 | C15: =SUM(C11:C14) -> 645.43 | D15: =SUM(D11:D14) -> 953.5
A16: Rohgewinn (EBIT) | B16: =B9-B15 -> -44.15 | C16: =C9-C15 -> 1349.57 | D16: =D9-D15 -> 6171.5
A17: Marge (%) | B17: =IFERROR(B16/B9,0) -> -0.092947368 | C17: =IFERROR(C16/C9,0) -> 0.67647619 | D17: =IFERROR(D16/D9,0) -> 0.86617544

Sheet Break-Even
A1: Break-Even Analyse
A2: Wie viele Kunden / User brauchst du, um profitabel zu sein?
A4: FIXKOSTEN / MONAT
A5: Infrastruktur | B5: =Annahmen!B11 -> 60
A6: Entwicklung | B6: =Annahmen!B15 -> 400
A7: Summe Fixkosten | B7: =SUM(B5:B6) -> 460
A9: VARIABLE KOSTEN JE ACCOUNT
A10: Stripe-Kosten (Ø je Account) | B10: =Annahmen!B5*Annahmen!B6*Annahmen!B12+Annahmen!B13 -> 0.782
A11: Support je Account | B11: =Annahmen!B14 -> 5
A12: Summe variable Kosten / Account | B12: =SUM(B10:B11) -> 5.782
A14: BREAK-EVEN ERGEBNIS
A15: MRR je Account (Ø, Mindest-User) | B15: =Annahmen!B5*Annahmen!B6 -> 38
A16: Deckungsbeitrag je Account | B16: =B15-B12 -> 32.218
A17: Break-Even Accounts (gerundet auf ganze Zahl) | B17: =IFERROR(CEILING(B7/B16,1),"n/v") -> 15
A18: Break-Even User gesamt | B18: =IFERROR(B17*Annahmen!B6,"n/v") -> 30
A19: Break-Even MRR | B19: =IFERROR(B17*B15,"n/v") -> 570

Sheet 12-Monate
A1: 12-Monats MRR-Projektion
A2: WACHSTUMS-ANNAHMEN
A3: Neue Kunden / Monat (Start) | B3: 3
A4: Wachstum neue Kunden / Monat | B4: 0.05
A5: Churn Rate / Monat | B5: 0.02
A7: KENNZAHL | B7: Jan | C7: Feb | D7: Mär | E7: Apr | F7: Mai | G7: Jun | H7: Jul | I7: Aug | J7: Sep | K7: Okt | L7: Nov | M7: Dez
A8: Neue Kunden | B8: =$B$3 -> 3 | C8: =ROUND(B8*(1+$B$4),0) -> 3 | D8: =ROUND(C8*(1+$B$4),0) -> 3 | E8: =ROUND(D8*(1+$B$4),0) -> 3 | F8: =ROUND(E8*(1+$B$4),0) -> 3 | G8: =ROUND(F8*(1+$B$4),0) -> 3 | H8: =ROUND(G8*(1+$B$4),0) -> 3 | I8: =ROUND(H8*(1+$B$4),0) -> 3 | J8: =ROUND(I8*(1+$B$4),0) -> 3 | ... M8: =ROUND(L8*(1+$B$4),0) -> 3
A9: Kunden (kumuliert) | B9: =B8 -> 3 | C9: =B11+C8 -> 6 | D9: =C11+D8 -> 9 | E9: =D11+E8 -> 12 | F9: =E11+F8 -> 15 | G9: =F11+G8 -> 18 | H9: =G11+H8 -> 21 | I9: =H11+I8 -> 24 | J9: =I11+J8 -> 27 | ... M9: =L11+M8 -> 34
A10: Churn (Abgänge) | B10: =ROUND(B9*$B$5,0) -> 0 | C10: =ROUND(B11*$B$5,0) -> 0 | D10: =ROUND(C11*$B$5,0) -> 0 | E10: =ROUND(D11*$B$5,0) -> 0 | F10: =ROUND(E11*$B$5,0) -> 0 | G10: =ROUND(F11*$B$5,0) -> 0 | H10: =ROUND(G11*$B$5,0) -> 0 | I10: =ROUND(H11*$B$5,0) -> 0 | J10: =ROUND(I11*$B$5,0) -> 0 | ... M10: =ROUND(L11*$B$5,0) -> 1
A11: Aktive Kunden (EoM) | B11: =B9-B10 -> 3 | C11: =C9-C10 -> 6 | D11: =D9-D10 -> 9 | E11: =E9-E10 -> 12 | F11: =F9-F10 -> 15 | G11: =G9-G10 -> 18 | H11: =H9-H10 -> 21 | I11: =I9-I10 -> 24 | ... M11: =M9-M10 -> 33
A12: MRR | B12: =B11*Annahmen!B5*Annahmen!B6 -> 114 | C12: =C11*Annahmen!B5*Annahmen!B6 -> 228 | D12: =D11*Annahmen!B5*Annahmen!B6 -> 342 | E12: =E11*Annahmen!B5*Annahmen!B6 -> 456 | F12: =F11*Annahmen!B5*Annahmen!B6 -> 570 | G12: =G11*Annahmen!B5*Annahmen!B6 -> 684 | H12: =H11*Annahmen!B5*Annahmen!B6 -> 798 | I12: =I11*Annahmen!B5*Annahmen!B6 -> 912 | J12: =J11*Annahmen!B5*Annahmen!B6 -> 1026 | K12: =K11*Annahmen!B5*Annahmen!B6 -> 1102 | L12: =L11*Annahmen!B5*Annahmen!B6 -> 1178 | M12: =M11*Annahmen!B5*Annahmen!B6 -> 1254
A13: ARR (annualisiert) | B13: =B12*12 -> 1368 | C13: =C12*12 -> 2736 | D13: =D12*12 -> 4104 | E13: =E12*12 -> 5472 | F13: =F12*12 -> 6840 | G13: =G12*12 -> 8208 | H13: =H12*12 -> 9576 | I13: =I12*12 -> 10944 | ... M13: =M12*12 -> 15048

Sheet Prognose
A1: FieldApp SHK – Umsatzprognose (18 Monate)
A2: ANNAHMEN
A3: Pre-Launch Monate (kein Umsatz) | B3: 2 | C3: Zeitraum Multi-User-Entwicklung
A4: Neue Kunden / Monat (Start) | B4: 3 | C4: Netzwerk-Validierung
A5: Wachstum neue Kunden / Monat | B5: 0.05 | C5: 5 % = 1 Kunde mehr alle ~4 Monate
A6: Churn Rate / Monat (Base Case) | B6: 0.02 | C6: 2 % Basis; Sensitivität auf Sheet 2
A7: MRR-Meilenstein 1 | B7: 1000 | C7: Ziel: €1.000 MRR
A8: MRR-Meilenstein 2 | B8: 5000 | C8: Ziel: €5.000 MRR
A10: KENNZAHL | B10: Ziel | C10: Hinweis | D10: M1 | E10: M2 | F10: M3 | G10: M4 | H10: M5 | I10: M6 | J10: M7 | K10: M8 | L10: M9 | M10: M10 | N10: M11 | O10: M12 | P10: M13 | Q10: M14 | R10: M15 | S10: M16 | T10: M17 | U10: M18
A11: Phase | C11: Pre-Launch / Live | D11: =IF(1<=$B$3,"Pre-Launch","Live") -> Pre-Launch | E11: =IF(2<=$B$3,"Pre-Launch","Live") -> Pre-Launch | F11: =IF(3<=$B$3,"Pre-Launch","Live") -> Live | G11: =IF(4<=$B$3,"Pre-Launch","Live") -> Live | H11: =IF(5<=$B$3,"Pre-Launch","Live") -> Live | I11: =IF(6<=$B$3,"Pre-Launch","Live") -> Live | J11: =IF(7<=$B$3,"Pre-Launch","Live") -> Live | K11: =IF(8<=$B$3,"Pre-Launch","Live") -> Live | L11: =IF(9<=$B$3,"Pre-Launch","Live") -> Live | M11: =IF(10<=$B$3,"Pre-Launch","Live") -> Live | N11: =IF(11<=$B$3,"Pre-Launch","Live") -> Live | O11: =IF(12<=$B$3,"Pre-Launch","Live") -> Live | P11: =IF(13<=$B$3,"Pre-Launch","Live") -> Live | Q11: =IF(14<=$B$3,"Pre-Launch","Live") -> Live | R11: =IF(15<=$B$3,"Pre-Launch","Live") -> Live | S11: =IF(16<=$B$3,"Pre-Launch","Live") -> Live | T11: =IF(17<=$B$3,"Pre-Launch","Live") -> Live | U11: =IF(18<=$B$3,"Pre-Launch","Live") -> Live
A12: Neue Kunden | D12: =IF(1<=$B$3,0,$B$4) -> 0 | E12: =IF(2<=$B$3,0,ROUND(D12*(1+$B$5),0)) -> 0 | F12: =IF(3<=$B$3,0,ROUND(E12*(1+$B$5),0)) -> 0 | G12: =IF(4<=$B$3,0,ROUND(F12*(1+$B$5),0)) -> 0 | H12: =IF(5<=$B$3,0,ROUND(G12*(1+$B$5),0)) -> 0 | I12: =IF(6<=$B$3,0,ROUND(H12*(1+$B$5),0)) -> 0 | J12: =IF(7<=$B$3,0,ROUND(I12*(1+$B$5),0)) -> 0 | K12: =IF(8<=$B$3,0,ROUND(J12*(1+$B$5),0)) -> 0 | L12: =IF(9<=$B$3,0,ROUND(K12*(1+$B$5),0)) -> 0 | M12: =IF(10<=$B$3,0,ROUND(L12*(1+$B$5),0)) -> 0 | N12: =IF(11<=$B$3,0,ROUND(M12*(1+$B$5),0)) -> 0 | O12: =IF(12<=$B$3,0,ROUND(N12*(1+$B$5),0)) -> 0 | P12: =IF(13<=$B$3,0,ROUND(O12*(1+$B$5),0)) -> 0 | Q12: =IF(14<=$B$3,0,ROUND(P12*(1+$B$5),0)) -> 0 | R12: =IF(15<=$B$3,0,ROUND(Q12*(1+$B$5),0)) -> 0 | S12: =IF(16<=$B$3,0,ROUND(R12*(1+$B$5),0)) -> 0 | T12: =IF(17<=$B$3,0,ROUND(S12*(1+$B$5),0)) -> 0 | U12: =IF(18<=$B$3,0,ROUND(T12*(1+$B$5),0)) -> 0
A13: Aktive Kunden (EoM) | D13: =IF(1<=$B$3,0,D12) -> 0 | E13: =IF(2<=$B$3,0,MAX(0,D13*(1-$B$6)+E12)) -> 0 | F13: =IF(3<=$B$3,0,MAX(0,E13*(1-$B$6)+F12)) -> 0 | G13: =IF(4<=$B$3,0,MAX(0,F13*(1-$B$6)+G12)) -> 0 | H13: =IF(5<=$B$3,0,MAX(0,G13*(1-$B$6)+H12)) -> 0 | I13: =IF(6<=$B$3,0,MAX(0,H13*(1-$B$6)+I12)) -> 0 | J13: =IF(7<=$B$3,0,MAX(0,I13*(1-$B$6)+J12)) -> 0 | K13: =IF(8<=$B$3,0,MAX(0,J13*(1-$B$6)+K12)) -> 0 | L13: =IF(9<=$B$3,0,MAX(0,K13*(1-$B$6)+L12)) -> 0 | M13: =IF(10<=$B$3,0,MAX(0,L13*(1-$B$6)+M12)) -> 0 | N13: =IF(11<=$B$3,0,MAX(0,M13*(1-$B$6)+N12)) -> 0 | O13: =IF(12<=$B$3,0,MAX(0,N13*(1-$B$6)+O12)) -> 0 | P13: =IF(13<=$B$3,0,MAX(0,O13*(1-$B$6)+P12)) -> 0 | Q13: =IF(14<=$B$3,0,MAX(0,P13*(1-$B$6)+Q12)) -> 0 | R13: =IF(15<=$B$3,0,MAX(0,Q13*(1-$B$6)+R12)) -> 0 | S13: =IF(16<=$B$3,0,MAX(0,R13*(1-$B$6)+S12)) -> 0 | T13: =IF(17<=$B$3,0,MAX(0,S13*(1-$B$6)+T12)) -> 0 | U13: =IF(18<=$B$3,0,MAX(0,T13*(1-$B$6)+U12)) -> 0
A14: MRR | B14: =B7 -> 1000 | D14: =IF(1<=$B$3,0,D13*Annahmen!$B$5*Annahmen!$B$6) -> 0 | E14: =IF(2<=$B$3,0,E13*Annahmen!$B$5*Annahmen!$B$6) -> 0 | F14: =IF(3<=$B$3,0,F13*Annahmen!$B$5*Annahmen!$B$6) -> 0 | G14: =IF(4<=$B$3,0,G13*Annahmen!$B$5*Annahmen!$B$6) -> 0 | H14: =IF(5<=$B$3,0,H13*Annahmen!$B$5*Annahmen!$B$6) -> 0 | I14: =IF(6<=$B$3,0,I13*Annahmen!$B$5*Annahmen!$B$6) -> 0 | J14: =IF(7<=$B$3,0,J13*Annahmen!$B$5*Annahmen!$B$6) -> 0 | K14: =IF(8<=$B$3,0,K13*Annahmen!$B$5*Annahmen!$B$6) -> 0 | L14: =IF(9<=$B$3,0,L13*Annahmen!$B$5*Annahmen!$B$6) -> 0 | M14: =IF(10<=$B$3,0,M13*Annahmen!$B$5*Annahmen!$B$6) -> 0 | N14: =IF(11<=$B$3,0,N13*Annahmen!$B$5*Annahmen!$B$6) -> 0 | O14: =IF(12<=$B$3,0,O13*Annahmen!$B$5*Annahmen!$B$6) -> 0 | P14: =IF(13<=$B$3,0,P13*Annahmen!$B$5*Annahmen!$B$6) -> 0 | Q14: =IF(14<=$B$3,0,Q13*Annahmen!$B$5*Annahmen!$B$6) -> 0 | R14: =IF(15<=$B$3,0,R13*Annahmen!$B$5*Annahmen!$B$6) -> 0 | S14: =IF(16<=$B$3,0,S13*Annahmen!$B$5*Annahmen!$B$6) -> 0 | T14: =IF(17<=$B$3,0,T13*Annahmen!$B$5*Annahmen!$B$6) -> 0 | U14: =IF(18<=$B$3,0,U13*Annahmen!$B$5*Annahmen!$B$6) -> 0
A15: Fixkosten | D15: =IF(1<=$B$3,Annahmen!$B$11+Annahmen!$B$15,Annahmen!$B$11+Annahmen!$B$15) -> 460 | E15: =IF(2<=$B$3,Annahmen!$B$11+Annahmen!$B$15,Annahmen!$B$11+Annahmen!$B$15) -> 460 | F15: =IF(3<=$B$3,Annahmen!$B$11+Annahmen!$B$15,Annahmen!$B$11+Annahmen!$B$15) -> 460 | G15: =IF(4<=$B$3,Annahmen!$B$11+Annahmen!$B$15,Annahmen!$B$11+Annahmen!$B$15) -> 460 | H15: =IF(5<=$B$3,Annahmen!$B$11+Annahmen!$B$15,Annahmen!$B$11+Annahmen!$B$15) -> 460 | I15: =IF(6<=$B$3,Annahmen!$B$11+Annahmen!$B$15,Annahmen!$B$11+Annahmen!$B$15) -> 460 | J15: =IF(7<=$B$3,Annahmen!$B$11+Annahmen!$B$15,Annahmen!$B$11+Annahmen!$B$15) -> 460 | K15: =IF(8<=$B$3,Annahmen!$B$11+Annahmen!$B$15,Annahmen!$B$11+Annahmen!$B$15) -> 460 | L15: =IF(9<=$B$3,Annahmen!$B$11+Annahmen!$B$15,Annahmen!$B$11+Annahmen!$B$15) -> 460 | M15: =IF(10<=$B$3,Annahmen!$B$11+Annahmen!$B$15,Annahmen!$B$11+Annahmen!$B$15) -> 460 | N15: =IF(11<=$B$3,Annahmen!$B$11+Annahmen!$B$15,Annahmen!$B$11+Annahmen!$B$15) -> 460 | O15: =IF(12<=$B$3,Annahmen!$B$11+Annahmen!$B$15,Annahmen!$B$11+Annahmen!$B$15) -> 460 | P15: =IF(13<=$B$3,Annahmen!$B$11+Annahmen!$B$15,Annahmen!$B$11+Annahmen!$B$15) -> 460 | Q15: =IF(14<=$B$3,Annahmen!$B$11+Annahmen!$B$15,Annahmen!$B$11+Annahmen!$B$15) -> 460 | R15: =IF(15<=$B$3,Annahmen!$B$11+Annahmen!$B$15,Annahmen!$B$11+Annahmen!$B$15) -> 460 | S15: =IF(16<=$B$3,Annahmen!$B$11+Annahmen!$B$15,Annahmen!$B$11+Annahmen!$B$15) -> 460 | T15: =IF(17<=$B$3,Annahmen!$B$11+Annahmen!$B$15,Annahmen!$B$11+Annahmen!$B$15) -> 460 | U15: =IF(18<=$B$3,Annahmen!$B$11+Annahmen!$B$15,Annahmen!$B$11+Annahmen!$B$15) -> 460
A16: Variable Kosten | D16: =IF(1<=$B$3,0,(D14*Annahmen!$B$12)+(D13*Annahmen!$B$13)+(D13*Annahmen!$B$14)) -> 0 | E16: =IF(2<=$B$3,0,(E14*Annahmen!$B$12)+(E13*Annahmen!$B$13)+(E13*Annahmen!$B$14)) -> 0 | F16: =IF(3<=$B$3,0,(F14*Annahmen!$B$12)+(F13*Annahmen!$B$13)+(F13*Annahmen!$B$14)) -> 0 | G16: =IF(4<=$B$3,0,(G14*Annahmen!$B$12)+(G13*Annahmen!$B$13)+(G13*Annahmen!$B$14)) -> 0 | H16: =IF(5<=$B$3,0,(H14*Annahmen!$B$12)+(H13*Annahmen!$B$13)+(H13*Annahmen!$B$14)) -> 0 | I16: =IF(6<=$B$3,0,(I14*Annahmen!$B$12)+(I13*Annahmen!$B$13)+(I13*Annahmen!$B$14)) -> 0 | J16: =IF(7<=$B$3,0,(J14*Annahmen!$B$12)+(J13*Annahmen!$B$13)+(J13*Annahmen!$B$14)) -> 0 | K16: =IF(8<=$B$3,0,(K14*Annahmen!$B$12)+(K13*Annahmen!$B$13)+(K13*Annahmen!$B$14)) -> 0 | L16: =IF(9<=$B$3,0,(L14*Annahmen!$B$12)+(L13*Annahmen!$B$13)+(L13*Annahmen!$B$14)) -> 0 | M16: =IF(10<=$B$3,0,(M14*Annahmen!$B$12)+(M13*Annahmen!$B$13)+(M13*Annahmen!$B$14)) -> 0 | N16: =IF(11<=$B$3,0,(N14*Annahmen!$B$12)+(N13*Annahmen!$B$13)+(N13*Annahmen!$B$14)) -> 0 | O16: =IF(12<=$B$3,0,(O14*Annahmen!$B$12)+(O13*Annahmen!$B$13)+(O13*Annahmen!$B$14)) -> 0 | P16: =IF(13<=$B$3,0,(P14*Annahmen!$B$12)+(P13*Annahmen!$B$13)+(P13*Annahmen!$B$14)) -> 0 | Q16: =IF(14<=$B$3,0,(Q14*Annahmen!$B$12)+(Q13*Annahmen!$B$13)+(Q13*Annahmen!$B$14)) -> 0 | R16: =IF(15<=$B$3,0,(R14*Annahmen!$B$12)+(R13*Annahmen!$B$13)+(R13*Annahmen!$B$14)) -> 0 | S16: =IF(16<=$B$3,0,(S14*Annahmen!$B$12)+(S13*Annahmen!$B$13)+(S13*Annahmen!$B$14)) -> 0 | T16: =IF(17<=$B$3,0,(T14*Annahmen!$B$12)+(T13*Annahmen!$B$13)+(T13*Annahmen!$B$14)) -> 0 | U16: =IF(18<=$B$3,0,(U14*Annahmen!$B$12)+(U13*Annahmen!$B$13)+(U13*Annahmen!$B$14)) -> 0
A17: Gesamtkosten | D17: =D15+D16 -> 460 | E17: =E15+E16 -> 460 | F17: =F15+F16 -> 460 | G17: =G15+G16 -> 460 | H17: =H15+H16 -> 460 | I17: =I15+I16 -> 460 | J17: =J15+J16 -> 460 | K17: =K15+K16 -> 460 | ... U17: =U15+U16 -> 460
A18: Gewinn / Verlust | D18: =D14-D17 -> -460 | E18: =E14-E17 -> -460 | F18: =F14-F17 -> -460 | G18: =G14-G17 -> -460 | H18: =H14-H17 -> -460 | I18: =I14-I17 -> -460 | J18: =J14-J17 -> -460 | K18: =K14-K17 -> -460 | ... U18: =U14-U17 -> -460
A19: Kumulierter Gewinn | D19: =D18 -> -460 | E19: =D19+E18 -> -920 | F19: =E19+F18 -> -1380 | G19: =F19+G18 -> -1840 | H19: =G19+H18 -> -2300 | I19: =H19+I18 -> -2760 | J19: =I19+J18 -> -3220 | K19: =J19+K18 -> -3680 | L19: =K19+L18 -> -4140 | ... U19: =T19+U18 -> -8280
A20: Meilenstein erreicht? | D20: =IF(D14=0,"–",IF(D14>=$B$8,"🏆 €5k",IF(D14>=$B$7,"✅ €1k",""))) -> – | E20: =IF(E14=0,"–",IF(E14>=$B$8,"🏆 €5k",IF(E14>=$B$7,"✅ €1k",""))) -> – | F20: =IF(F14=0,"–",IF(F14>=$B$8,"🏆 €5k",IF(F14>=$B$7,"✅ €1k",""))) -> – | G20: =IF(G14=0,"–",IF(G14>=$B$8,"🏆 €5k",IF(G14>=$B$7,"✅ €1k",""))) -> – | H20: =IF(H14=0,"–",IF(H14>=$B$8,"🏆 €5k",IF(H14>=$B$7,"✅ €1k",""))) -> – | I20: =IF(I14=0,"–",IF(I14>=$B$8,"🏆 €5k",IF(I14>=$B$7,"✅ €1k",""))) -> – | J20: =IF(J14=0,"–",IF(J14>=$B$8,"🏆 €5k",IF(J14>=$B$7,"✅ €1k",""))) -> – | K20: =IF(K14=0,"–",IF(K14>=$B$8,"🏆 €5k",IF(K14>=$B$7,"✅ €1k",""))) -> – | ... U20: =IF(U14=0,"–",IF(U14>=$B$8,"🏆 €5k",IF(U14>=$B$7,"✅ €1k",""))) -> –
A22: * Grau hinterlegte Monate = Pre-Launch (Entwicklung, kein Umsatz). Fixkosten laufen trotzdem.

Sheet Churn-Sensitivität
A1: Churn-Sensitivitätsanalyse
A2: Wie verändert sich MRR in Monat 12 bei unterschiedlichem Churn und Wachstum?
A3: Churn-Rate (Zeilen) × Neue Kunden/Monat Start (Spalten) → MRR Monat 12 (nach Pre-Launch)
A5: Churn / Neue Kd. | B5: 2 Kunden/Mt. | C5: 3 Kunden/Mt. | D5: 4 Kunden/Mt. | E5: 6 Kunden/Mt. | F5: 8 Kunden/Mt.
A6: Churn 1% / Mt. | B6: 1122 | C6: 1702 | D6: 2317 | E6: 3437 | F6: 4597
A7: Churn 2% / Mt. | B7: 1069 | C7: 1622 | D7: 2210 | E7: 3275 | F7: 4381
A8: Churn 3% / Mt. | B8: 1019 | C8: 1548 | D8: 2109 | E8: 3123 | F8: 4179
A9: Churn 5% / Mt. | B9: 928 | C9: 1412 | D9: 1924 | E9: 2845 | F9: 3810
A10: Churn 8% / Mt. | B10: 811 | C10: 1237 | D10: 1687 | E10: 2489 | F10: 3335
A11: Churn 12% / Mt. | B11: 684 | C11: 1049 | D11: 1431 | E11: 2104 | F11: 2824
A13: 🔴 < €800 MRR · 🟠 €800–€2.000 · 🟢 > €2.000 MRR
A14: Gelb markierte Zeile = Base Case (2 % Churn, 3 Neue Kunden/Monat aus Prognose-Sheet)
A15: Hinweis: Alle Werte nach 12 aktiven Monaten (ohne Pre-Launch-Phase). Wachstum neue Kunden: 5 %/Monat.
